redisx/__init__.py
redisx/ann_faiss.py
redisx/ann_hnswcore.py
redisx/ann_usearch.py
redisx/client.py
redisx/commands.py
redisx/define.py
redisx/pipeline.py
redisx/slot_mgrt.py
redisx-0.1.7.dist-info/LICENSE
redisx-0.1.7.dist-info/METADATA
redisx-0.1.7.dist-info/WHEEL
redisx-0.1.7.dist-info/top_level.txt
redisx-0.1.7.dist-info/RECORD
