Metadata-Version: 2.1
Name: redisx
Version: 0.1.7
Summary: Python client for RedisX
Home-page: https://github.com/weedge/redisx-py
Author: weedge
Author-email: weege007@gmail.com
License: MIT
Requires-Python: >=3.10
License-File: LICENSE
Requires-Dist: redis ==5.0.0
